brixo/__init__.py
brixo/brixo_tracer_provider.py
brixo/filtering_by_scope_span_processor.py
brixo/instrumentation.py
brixo-0.1.3.dist-info/WHEEL
brixo-0.1.3.dist-info/METADATA
brixo-0.1.3.dist-info/RECORD
