Metadata-Version: 2.3
Name: brixo
Version: 0.1.3
Summary: The Brixo Python SDK
Author: Brixo Engineering
Author-email: Brixo Engineering <sdk@brixo.com>
Requires-Dist: openinference-instrumentation-langchain>=0.1.55
Requires-Dist: openinference-instrumentation-openai>=0.1.41
Requires-Dist: opentelemetry-exporter-otlp>=1.38.0
Requires-Dist: opentelemetry-sdk>=1.38.0
Requires-Dist: traceloop-sdk>=0.49.2
Requires-Dist: bandit>=1.7.7 ; extra == 'dev'
Requires-Dist: mypy>=1.10.0 ; extra == 'dev'
Requires-Dist: pip-audit>=2.7.2 ; extra == 'dev'
Requires-Dist: pre-commit>=4.5.1 ; extra == 'dev'
Requires-Dist: pytest>=9.0.1 ; extra == 'dev'
Requires-Dist: ruff>=0.6.9 ; extra == 'dev'
Requires-Dist: twine>=5.1.1 ; extra == 'dev'
Requires-Python: >=3.10.0, <4
Provides-Extra: dev
